pymetdecoder/__init__.py
pymetdecoder/code_tables.py
pymetdecoder/conversion.py
pymetdecoder/synop/__init__.py
pymetdecoder/synop/observations.py
pymetdecoder-0.1.6.dist-info/LICENSE.md
pymetdecoder-0.1.6.dist-info/METADATA
pymetdecoder-0.1.6.dist-info/WHEEL
pymetdecoder-0.1.6.dist-info/top_level.txt
pymetdecoder-0.1.6.dist-info/RECORD
