Metadata-Version: 2.1
Name: pymetdecoder
Version: 0.1.6
Summary: Python module to decode/encode met reports e.g. SYNOPs
Home-page: https://github.com/antarctica/pymetdecoder
Author: Tim Barnes
Author-email: tdba@bas.ac.uk
License: Open Government License v3.0
Classifier: Development Status :: 5 - Production/Stable
Classifier: Intended Audience :: Science/Research
Classifier: License :: Other/Proprietary License
Classifier: Programming Language :: Python :: 3
License-File: LICENSE.md
